[{"co_inscricao_enem":"19****5644100","no_inscrito":"MARUAN FOLETTO DA SILVA","nu_classificacao":"1","nu_nota_candidato":"671.72","qt_bonus_perc":".00","tp_mod_concorrencia":"A","co_mod_concorrencia":"0","no_mod_concorrencia":"Ampla concorr\u00eancia","co_legenda":null,"ds_legenda":null},{"co_inscricao_enem":"19****6564341","no_inscrito":"MARCELA FRACARO SASSO","nu_classificacao":"2","nu_nota_candidato":"664.02","qt_bonus_perc":".00","tp_mod_concorrencia":"A","co_mod_concorrencia":"0","no_mod_concorrencia":"Ampla concorr\u00eancia","co_legenda":null,"ds_legenda":null},{"co_inscricao_enem":"19****9330439","no_inscrito":"FERNANDA NACHTIGALL","nu_classificacao":"3","nu_nota_candidato":"656.74","qt_bonus_perc":".00","tp_mod_concorrencia":"A","co_mod_concorrencia":"0","no_mod_concorrencia":"Ampla concorr\u00eancia","co_legenda":null,"ds_legenda":null},{"co_inscricao_enem":"19****6110038","no_inscrito":"KAUAN GONCALVES SEVERO","nu_classificacao":"4","nu_nota_candidato":"650.76","qt_bonus_perc":".00","tp_mod_concorrencia":"A","co_mod_concorrencia":"0","no_mod_concorrencia":"Ampla concorr\u00eancia","co_legenda":null,"ds_legenda":null},{"co_inscricao_enem":"19****3985402","no_inscrito":"GABRIELA VIEIRA PONTALTI","nu_classificacao":"5","nu_nota_candidato":"648.42","qt_bonus_perc":".00","tp_mod_concorrencia":"A","co_mod_concorrencia":"0","no_mod_concorrencia":"Ampla concorr\u00eancia","co_legenda":null,"ds_legenda":null},{"co_inscricao_enem":"19****4127707","no_inscrito":"JULIANA PAGLIARINI DALLA POZZA","nu_classificacao":"6","nu_nota_candidato":"644.48","qt_bonus_perc":".00","tp_mod_concorrencia":"A","co_mod_concorrencia":"0","no_mod_concorrencia":"Ampla concorr\u00eancia","co_legenda":null,"ds_legenda":null},{"co_inscricao_enem":"19****4948118","no_inscrito":"HERMES TOBIAS SILVA DA SILVA","nu_classificacao":"7","nu_nota_candidato":"632.10","qt_bonus_perc":".00","tp_mod_concorrencia":"A","co_mod_concorrencia":"0","no_mod_concorrencia":"Ampla concorr\u00eancia","co_legenda":null,"ds_legenda":null},{"co_inscricao_enem":"19****1571659","no_inscrito":"MARIANA CUHR DAS NEVES","nu_classificacao":"8","nu_nota_candidato":"629.12","qt_bonus_perc":".00","tp_mod_concorrencia":"A","co_mod_concorrencia":"0","no_mod_concorrencia":"Ampla concorr\u00eancia","co_legenda":null,"ds_legenda":null},{"co_inscricao_enem":"19****5425633","no_inscrito":"VANESSA MARIA DA SILVA RIBEIRO","nu_classificacao":"9","nu_nota_candidato":"628.38","qt_bonus_perc":".00","tp_mod_concorrencia":"A","co_mod_concorrencia":"0","no_mod_concorrencia":"Ampla concorr\u00eancia","co_legenda":null,"ds_legenda":null},{"co_inscricao_enem":"19****2943923","no_inscrito":"GIULIA PIETRA PAIM DO ROSARIO","nu_classificacao":"10","nu_nota_candidato":"627.06","qt_bonus_perc":".00","tp_mod_concorrencia":"A","co_mod_concorrencia":"0","no_mod_concorrencia":"Ampla concorr\u00eancia","co_legenda":null,"ds_legenda":null},{"co_inscricao_enem":"19****3588119","no_inscrito":"NICOLE MARQUES BATISTA","nu_classificacao":"11","nu_nota_candidato":"625.42","qt_bonus_perc":".00","tp_mod_concorrencia":"A","co_mod_concorrencia":"0","no_mod_concorrencia":"Ampla concorr\u00eancia","co_legenda":null,"ds_legenda":null},{"co_inscricao_enem":"19****1859041","no_inscrito":"PAULA HOSCHETTE DEARO VALVERDE","nu_classificacao":"12","nu_nota_candidato":"624.36","qt_bonus_perc":".00","tp_mod_concorrencia":"A","co_mod_concorrencia":"0","no_mod_concorrencia":"Ampla concorr\u00eancia","co_legenda":null,"ds_legenda":null},{"co_inscricao_enem":"19****8619989","no_inscrito":"MARINA HARUMI WATANABE","nu_classificacao":"13","nu_nota_candidato":"623.80","qt_bonus_perc":".00","tp_mod_concorrencia":"A","co_mod_concorrencia":"0","no_mod_concorrencia":"Ampla concorr\u00eancia","co_legenda":null,"ds_legenda":null},{"co_inscricao_enem":"19****8630474","no_inscrito":"PEDRO HENRIQUE BIRAL FERNANDO","nu_classificacao":"14","nu_nota_candidato":"622.56","qt_bonus_perc":".00","tp_mod_concorrencia":"A","co_mod_concorrencia":"0","no_mod_concorrencia":"Ampla concorr\u00eancia","co_legenda":null,"ds_legenda":null},{"co_inscricao_enem":"19****0119713","no_inscrito":"JOAO MATHEUS FERRAZ PORTOLAN","nu_classificacao":"15","nu_nota_candidato":"615.28","qt_bonus_perc":".00","tp_mod_concorrencia":"A","co_mod_concorrencia":"0","no_mod_concorrencia":"Ampla concorr\u00eancia","co_legenda":null,"ds_legenda":null},{"co_inscricao_enem":"19****4171705","no_inscrito":"GUILHERME DE BONA DOS SANTOS","nu_classificacao":"16","nu_nota_candidato":"613.34","qt_bonus_perc":".00","tp_mod_concorrencia":"A","co_mod_concorrencia":"0","no_mod_concorrencia":"Ampla concorr\u00eancia","co_legenda":null,"ds_legenda":null},{"co_inscricao_enem":"19****8502133","no_inscrito":"LUCIANA SAMARA BRAZ MATOS","nu_classificacao":"17","nu_nota_candidato":"609.86","qt_bonus_perc":".00","tp_mod_concorrencia":"A","co_mod_concorrencia":"0","no_mod_concorrencia":"Ampla concorr\u00eancia","co_legenda":null,"ds_legenda":null},{"co_inscricao_enem":"19****0308267","no_inscrito":"HELLEN LUCIA BEHRENZ","nu_classificacao":"18","nu_nota_candidato":"603.94","qt_bonus_perc":".00","tp_mod_concorrencia":"A","co_mod_concorrencia":"0","no_mod_concorrencia":"Ampla concorr\u00eancia","co_legenda":null,"ds_legenda":null},{"co_inscricao_enem":"19****5356353","no_inscrito":"ITALO TAVARES CORDEIRO","nu_classificacao":"19","nu_nota_candidato":"598.52","qt_bonus_perc":".00","tp_mod_concorrencia":"A","co_mod_concorrencia":"0","no_mod_concorrencia":"Ampla concorr\u00eancia","co_legenda":null,"ds_legenda":null},{"co_inscricao_enem":"19****4522069","no_inscrito":"LEONARDO OGEA","nu_classificacao":"20","nu_nota_candidato":"597.90","qt_bonus_perc":".00","tp_mod_concorrencia":"A","co_mod_concorrencia":"0","no_mod_concorrencia":"Ampla concorr\u00eancia","co_legenda":null,"ds_legenda":null},{"co_inscricao_enem":"19****9786576","no_inscrito":"VITORIA GONCALVES DE LARA","nu_classificacao":"21","nu_nota_candidato":"595.70","qt_bonus_perc":".00","tp_mod_concorrencia":"A","co_mod_concorrencia":"0","no_mod_concorrencia":"Ampla concorr\u00eancia","co_legenda":null,"ds_legenda":null},{"co_inscricao_enem":"19****9781379","no_inscrito":"ARON SOUZA PONTES","nu_classificacao":"22","nu_nota_candidato":"595.46","qt_bonus_perc":".00","tp_mod_concorrencia":"A","co_mod_concorrencia":"0","no_mod_concorrencia":"Ampla concorr\u00eancia","co_legenda":null,"ds_legenda":null},{"co_inscricao_enem":"19****6228826","no_inscrito":"JENIFFER PRISCILLA DA SILVA FREITAS","nu_classificacao":"23","nu_nota_candidato":"594.46","qt_bonus_perc":".00","tp_mod_concorrencia":"A","co_mod_concorrencia":"0","no_mod_concorrencia":"Ampla concorr\u00eancia","co_legenda":null,"ds_legenda":null},{"co_inscricao_enem":"19****4917288","no_inscrito":"BIANCA TOMASIA MONTEIRO DOS SANTOS","nu_classificacao":"24","nu_nota_candidato":"587.70","qt_bonus_perc":".00","tp_mod_concorrencia":"A","co_mod_concorrencia":"0","no_mod_concorrencia":"Ampla concorr\u00eancia","co_legenda":null,"ds_legenda":null},{"co_inscricao_enem":"19****0532008","no_inscrito":"GELCIARA HAMMERSCHMITT","nu_classificacao":"25","nu_nota_candidato":"587.24","qt_bonus_perc":".00","tp_mod_concorrencia":"A","co_mod_concorrencia":"0","no_mod_concorrencia":"Ampla concorr\u00eancia","co_legenda":null,"ds_legenda":null},{"co_inscricao_enem":"19****1720123","no_inscrito":"MARCOS ANTONIO WOLLMUTH","nu_classificacao":"26","nu_nota_candidato":"583.16","qt_bonus_perc":".00","tp_mod_concorrencia":"A","co_mod_concorrencia":"0","no_mod_concorrencia":"Ampla concorr\u00eancia","co_legenda":null,"ds_legenda":null},{"co_inscricao_enem":"19****8454000","no_inscrito":"RAFAEL BACKES","nu_classificacao":"27","nu_nota_candidato":"582.52","qt_bonus_perc":".00","tp_mod_concorrencia":"A","co_mod_concorrencia":"0","no_mod_concorrencia":"Ampla concorr\u00eancia","co_legenda":null,"ds_legenda":null},{"co_inscricao_enem":"19****3600864","no_inscrito":"BRUNA DA SILVA ZANCHETA","nu_classificacao":"28","nu_nota_candidato":"572.66","qt_bonus_perc":".00","tp_mod_concorrencia":"A","co_mod_concorrencia":"0","no_mod_concorrencia":"Ampla concorr\u00eancia","co_legenda":null,"ds_legenda":null},{"co_inscricao_enem":"19****1795385","no_inscrito":"MAICON MACIEL ARAUJO SOUSA","nu_classificacao":"29","nu_nota_candidato":"568.46","qt_bonus_perc":".00","tp_mod_concorrencia":"A","co_mod_concorrencia":"0","no_mod_concorrencia":"Ampla concorr\u00eancia","co_legenda":null,"ds_legenda":null},{"co_inscricao_enem":"19****0320458","no_inscrito":"GEOVANA DE MOURA FORTES","nu_classificacao":"30","nu_nota_candidato":"562.00","qt_bonus_perc":".00","tp_mod_concorrencia":"A","co_mod_concorrencia":"0","no_mod_concorrencia":"Ampla concorr\u00eancia","co_legenda":null,"ds_legenda":null},{"co_inscricao_enem":"19****1658112","no_inscrito":"VITOR MATEUS VIEBRANTZ","nu_classificacao":"1","nu_nota_candidato":"665.06","qt_bonus_perc":".00","tp_mod_concorrencia":"L","co_mod_concorrencia":"1","no_mod_concorrencia":"Candidatos com renda familiar bruta per capita igual ou inferior a 1,5 sal\u00e1rio m\u00ednimo que tenham cursado integralmente o ensino m\u00e9dio em escolas p\u00fablicas (Lei n\u00ba 12.711\/2012).","co_legenda":null,"ds_legenda":null},{"co_inscricao_enem":"19****3015392","no_inscrito":"GRACIELA ROMANSIN JORIATTI","nu_classificacao":"2","nu_nota_candidato":"648.62","qt_bonus_perc":".00","tp_mod_concorrencia":"L","co_mod_concorrencia":"1","no_mod_concorrencia":"Candidatos com renda familiar bruta per capita igual ou inferior a 1,5 sal\u00e1rio m\u00ednimo que tenham cursado integralmente o ensino m\u00e9dio em escolas p\u00fablicas (Lei n\u00ba 12.711\/2012).","co_legenda":null,"ds_legenda":null},{"co_inscricao_enem":"19****3290769","no_inscrito":"ALINE CORACINI MALGARIN","nu_classificacao":"3","nu_nota_candidato":"638.22","qt_bonus_perc":".00","tp_mod_concorrencia":"L","co_mod_concorrencia":"1","no_mod_concorrencia":"Candidatos com renda familiar bruta per capita igual ou inferior a 1,5 sal\u00e1rio m\u00ednimo que tenham cursado integralmente o ensino m\u00e9dio em escolas p\u00fablicas (Lei n\u00ba 12.711\/2012).","co_legenda":null,"ds_legenda":null},{"co_inscricao_enem":"19****1498663","no_inscrito":"BRENDA RODRIGUES ALVES","nu_classificacao":"4","nu_nota_candidato":"635.32","qt_bonus_perc":".00","tp_mod_concorrencia":"L","co_mod_concorrencia":"1","no_mod_concorrencia":"Candidatos com renda familiar bruta per capita igual ou inferior a 1,5 sal\u00e1rio m\u00ednimo que tenham cursado integralmente o ensino m\u00e9dio em escolas p\u00fablicas (Lei n\u00ba 12.711\/2012).","co_legenda":null,"ds_legenda":null},{"co_inscricao_enem":"19****4221872","no_inscrito":"LEONARDO HENRIQUE MULLER GAMBIN","nu_classificacao":"5","nu_nota_candidato":"634.22","qt_bonus_perc":".00","tp_mod_concorrencia":"L","co_mod_concorrencia":"1","no_mod_concorrencia":"Candidatos com renda familiar bruta per capita igual ou inferior a 1,5 sal\u00e1rio m\u00ednimo que tenham cursado integralmente o ensino m\u00e9dio em escolas p\u00fablicas (Lei n\u00ba 12.711\/2012).","co_legenda":null,"ds_legenda":null},{"co_inscricao_enem":"19****1421358","no_inscrito":"HELENA VITORIA COLVARA CARDOSO","nu_classificacao":"6","nu_nota_candidato":"632.48","qt_bonus_perc":".00","tp_mod_concorrencia":"L","co_mod_concorrencia":"1","no_mod_concorrencia":"Candidatos com renda familiar bruta per capita igual ou inferior a 1,5 sal\u00e1rio m\u00ednimo que tenham cursado integralmente o ensino m\u00e9dio em escolas p\u00fablicas (Lei n\u00ba 12.711\/2012).","co_legenda":null,"ds_legenda":null},{"co_inscricao_enem":"19****9621712","no_inscrito":"LETICIA PINHEIRO","nu_classificacao":"7","nu_nota_candidato":"629.02","qt_bonus_perc":".00","tp_mod_concorrencia":"L","co_mod_concorrencia":"1","no_mod_concorrencia":"Candidatos com renda familiar bruta per capita igual ou inferior a 1,5 sal\u00e1rio m\u00ednimo que tenham cursado integralmente o ensino m\u00e9dio em escolas p\u00fablicas (Lei n\u00ba 12.711\/2012).","co_legenda":null,"ds_legenda":null},{"co_inscricao_enem":"19****3677389","no_inscrito":"LEONARDO DE OLIVEIRA MENDES","nu_classificacao":"1","nu_nota_candidato":"637.58","qt_bonus_perc":".00","tp_mod_concorrencia":"L","co_mod_concorrencia":"2","no_mod_concorrencia":"Candidatos autodeclarados pretos, pardos ou ind\u00edgenas, com renda familiar bruta per capita igual ou inferior a 1,5 sal\u00e1rio m\u00ednimo e que tenham cursado integralmente o ensino m\u00e9dio em escolas p\u00fablicas (Lei n\u00ba 12.711\/2012).","co_legenda":null,"ds_legenda":null},{"co_inscricao_enem":"19****3020200","no_inscrito":"JULIANA CRISTINY DA SILVA","nu_classificacao":"2","nu_nota_candidato":"607.72","qt_bonus_perc":".00","tp_mod_concorrencia":"L","co_mod_concorrencia":"2","no_mod_concorrencia":"Candidatos autodeclarados pretos, pardos ou ind\u00edgenas, com renda familiar bruta per capita igual ou inferior a 1,5 sal\u00e1rio m\u00ednimo e que tenham cursado integralmente o ensino m\u00e9dio em escolas p\u00fablicas (Lei n\u00ba 12.711\/2012).","co_legenda":null,"ds_legenda":null},{"co_inscricao_enem":"19****3810952","no_inscrito":"JULIANA MARIA DA SILVA","nu_classificacao":"3","nu_nota_candidato":"562.06","qt_bonus_perc":".00","tp_mod_concorrencia":"L","co_mod_concorrencia":"2","no_mod_concorrencia":"Candidatos autodeclarados pretos, pardos ou ind\u00edgenas, com renda familiar bruta per capita igual ou inferior a 1,5 sal\u00e1rio m\u00ednimo e que tenham cursado integralmente o ensino m\u00e9dio em escolas p\u00fablicas (Lei n\u00ba 12.711\/2012).","co_legenda":null,"ds_legenda":null},{"co_inscricao_enem":"19****0196452","no_inscrito":"THAINA FERNANDA BOTELHO DA SILVA ANACLETO","nu_classificacao":"4","nu_nota_candidato":"557.00","qt_bonus_perc":".00","tp_mod_concorrencia":"L","co_mod_concorrencia":"2","no_mod_concorrencia":"Candidatos autodeclarados pretos, pardos ou ind\u00edgenas, com renda familiar bruta per capita igual ou inferior a 1,5 sal\u00e1rio m\u00ednimo e que tenham cursado integralmente o ensino m\u00e9dio em escolas p\u00fablicas (Lei n\u00ba 12.711\/2012).","co_legenda":null,"ds_legenda":null},{"co_inscricao_enem":"19****1340939","no_inscrito":"VITORIA TROMBETTA KRZYZANIAK","nu_classificacao":"5","nu_nota_candidato":"556.68","qt_bonus_perc":".00","tp_mod_concorrencia":"L","co_mod_concorrencia":"2","no_mod_concorrencia":"Candidatos autodeclarados pretos, pardos ou ind\u00edgenas, com renda familiar bruta per capita igual ou inferior a 1,5 sal\u00e1rio m\u00ednimo e que tenham cursado integralmente o ensino m\u00e9dio em escolas p\u00fablicas (Lei n\u00ba 12.711\/2012).","co_legenda":null,"ds_legenda":null},{"co_inscricao_enem":"19****1513667","no_inscrito":"LARISSA WERLANG","nu_classificacao":"1","nu_nota_candidato":"653.06","qt_bonus_perc":".00","tp_mod_concorrencia":"L","co_mod_concorrencia":"5","no_mod_concorrencia":"Candidatos que, independentemente da renda (art. 14, II, Portaria Normativa n\u00ba 18\/2012), tenham cursado integralmente o ensino m\u00e9dio em escolas p\u00fablicas (Lei n\u00ba 12.711\/2012).","co_legenda":null,"ds_legenda":null},{"co_inscricao_enem":"19****5583736","no_inscrito":"JOAO HENRIQUE THOMAS KUHN","nu_classificacao":"2","nu_nota_candidato":"645.40","qt_bonus_perc":".00","tp_mod_concorrencia":"L","co_mod_concorrencia":"5","no_mod_concorrencia":"Candidatos que, independentemente da renda (art. 14, II, Portaria Normativa n\u00ba 18\/2012), tenham cursado integralmente o ensino m\u00e9dio em escolas p\u00fablicas (Lei n\u00ba 12.711\/2012).","co_legenda":null,"ds_legenda":null},{"co_inscricao_enem":"19****8321631","no_inscrito":"MATEUS BORBA QUINTEIRO","nu_classificacao":"3","nu_nota_candidato":"614.14","qt_bonus_perc":".00","tp_mod_concorrencia":"L","co_mod_concorrencia":"5","no_mod_concorrencia":"Candidatos que, independentemente da renda (art. 14, II, Portaria Normativa n\u00ba 18\/2012), tenham cursado integralmente o ensino m\u00e9dio em escolas p\u00fablicas (Lei n\u00ba 12.711\/2012).","co_legenda":null,"ds_legenda":null},{"co_inscricao_enem":"19****8674398","no_inscrito":"LUIZA GABRIELA PIRES BALEST","nu_classificacao":"4","nu_nota_candidato":"598.56","qt_bonus_perc":".00","tp_mod_concorrencia":"L","co_mod_concorrencia":"5","no_mod_concorrencia":"Candidatos que, independentemente da renda (art. 14, II, Portaria Normativa n\u00ba 18\/2012), tenham cursado integralmente o ensino m\u00e9dio em escolas p\u00fablicas (Lei n\u00ba 12.711\/2012).","co_legenda":null,"ds_legenda":null},{"co_inscricao_enem":"19****0965396","no_inscrito":"DANDARA DE SOUZA ALMEIDA","nu_classificacao":"5","nu_nota_candidato":"597.42","qt_bonus_perc":".00","tp_mod_concorrencia":"L","co_mod_concorrencia":"5","no_mod_concorrencia":"Candidatos que, independentemente da renda (art. 14, II, Portaria Normativa n\u00ba 18\/2012), tenham cursado integralmente o ensino m\u00e9dio em escolas p\u00fablicas (Lei n\u00ba 12.711\/2012).","co_legenda":null,"ds_legenda":null},{"co_inscricao_enem":"19****4443617","no_inscrito":"KAMYLLE MELISSA HELLER","nu_classificacao":"6","nu_nota_candidato":"596.26","qt_bonus_perc":".00","tp_mod_concorrencia":"L","co_mod_concorrencia":"5","no_mod_concorrencia":"Candidatos que, independentemente da renda (art. 14, II, Portaria Normativa n\u00ba 18\/2012), tenham cursado integralmente o ensino m\u00e9dio em escolas p\u00fablicas (Lei n\u00ba 12.711\/2012).","co_legenda":null,"ds_legenda":null},{"co_inscricao_enem":"19****3681506","no_inscrito":"ALEXANDRE CASSOL","nu_classificacao":"7","nu_nota_candidato":"590.56","qt_bonus_perc":".00","tp_mod_concorrencia":"L","co_mod_concorrencia":"5","no_mod_concorrencia":"Candidatos que, independentemente da renda (art. 14, II, Portaria Normativa n\u00ba 18\/2012), tenham cursado integralmente o ensino m\u00e9dio em escolas p\u00fablicas (Lei n\u00ba 12.711\/2012).","co_legenda":null,"ds_legenda":null},{"co_inscricao_enem":"19****0804455","no_inscrito":"KAUANY TAINAH FRIGHETTO","nu_classificacao":"1","nu_nota_candidato":"613.44","qt_bonus_perc":".00","tp_mod_concorrencia":"L","co_mod_concorrencia":"6","no_mod_concorrencia":"Candidatos autodeclarados pretos, pardos ou ind\u00edgenas que, independentemente da renda (art. 14, II, Portaria Normativa n\u00ba 18\/2012), tenham cursado integralmente o ensino m\u00e9dio em escolas p\u00fablicas (Lei n\u00ba 12.711\/2012).","co_legenda":null,"ds_legenda":null},{"co_inscricao_enem":"19****5457979","no_inscrito":"NATHAN MARTINS","nu_classificacao":"2","nu_nota_candidato":"570.00","qt_bonus_perc":".00","tp_mod_concorrencia":"L","co_mod_concorrencia":"6","no_mod_concorrencia":"Candidatos autodeclarados pretos, pardos ou ind\u00edgenas que, independentemente da renda (art. 14, II, Portaria Normativa n\u00ba 18\/2012), tenham cursado integralmente o ensino m\u00e9dio em escolas p\u00fablicas (Lei n\u00ba 12.711\/2012).","co_legenda":null,"ds_legenda":null},{"co_inscricao_enem":"19****2037621","no_inscrito":"ELIZANGELA DE ALMEIDA SANTOS","nu_classificacao":"3","nu_nota_candidato":"556.74","qt_bonus_perc":".00","tp_mod_concorrencia":"L","co_mod_concorrencia":"6","no_mod_concorrencia":"Candidatos autodeclarados pretos, pardos ou ind\u00edgenas que, independentemente da renda (art. 14, II, Portaria Normativa n\u00ba 18\/2012), tenham cursado integralmente o ensino m\u00e9dio em escolas p\u00fablicas (Lei n\u00ba 12.711\/2012).","co_legenda":null,"ds_legenda":null},{"co_inscricao_enem":"19****7986116","no_inscrito":"MARIANA ALVES RIBEIRO TACIANO","nu_classificacao":"4","nu_nota_candidato":"541.28","qt_bonus_perc":".00","tp_mod_concorrencia":"L","co_mod_concorrencia":"6","no_mod_concorrencia":"Candidatos autodeclarados pretos, pardos ou ind\u00edgenas que, independentemente da renda (art. 14, II, Portaria Normativa n\u00ba 18\/2012), tenham cursado integralmente o ensino m\u00e9dio em escolas p\u00fablicas (Lei n\u00ba 12.711\/2012).","co_legenda":null,"ds_legenda":null},{"co_inscricao_enem":"19****9733976","no_inscrito":"SAMUEL BENITES DE SOUSA","nu_classificacao":"5","nu_nota_candidato":"538.96","qt_bonus_perc":".00","tp_mod_concorrencia":"L","co_mod_concorrencia":"6","no_mod_concorrencia":"Candidatos autodeclarados pretos, pardos ou ind\u00edgenas que, independentemente da renda (art. 14, II, Portaria Normativa n\u00ba 18\/2012), tenham cursado integralmente o ensino m\u00e9dio em escolas p\u00fablicas (Lei n\u00ba 12.711\/2012).","co_legenda":null,"ds_legenda":null},{"co_inscricao_enem":"19****1710194","no_inscrito":"MATEUS AUGUSTO GOLDMEYER","nu_classificacao":"1","nu_nota_candidato":"602.52","qt_bonus_perc":".00","tp_mod_concorrencia":"L","co_mod_concorrencia":"13","no_mod_concorrencia":"Candidatos com defici\u00eancia que, independentemente da renda (art. 14, II, Portaria Normativa n\u00ba 18\/2012), tenham cursado integralmente o ensino m\u00e9dio em escolas p\u00fablicas (Lei n\u00ba 12.711\/2012).","co_legenda":null,"ds_legenda":null}]