{"search_rule":"DESIGN GR\u00c1FICO","0":{"co_oferta":"127282","co_termo_adesao":"2890","co_ies":"584","co_curso":"1188875","no_curso":"DESIGN GR\u00c1FICO","qt_vagas_sem1":"35","qt_vagas_sem2":"0","co_grau":"10049","no_grau":"Bacharelado","co_turno":"10068","no_turno":"Vespertino","st_turno_m":"0","st_turno_v":"1","st_turno_n":"0","ds_documentacao":"1.\tDOCUMENTA\u00c7\u00c3O B\u00c1SICA \r\nDocumentos para a matr\u00edcula\r\nI.\tDocumentos Pessoais: \r\na) formul\u00e1rio socioecon\u00f4mico preenchido no endere\u00e7o eletr\u00f4nico www.sisu.ufg.br  (n\u00e3o \u00e9 necess\u00e1ria a impress\u00e3o do documento);\r\nb) documento de identifica\u00e7\u00e3o (original e uma fotoc\u00f3pia). O candidato nascido fora do Brasil dever\u00e1 apresentar passaporte e a certid\u00e3o de nascimento (original e uma fotoc\u00f3pia) - OBRIGAT\u00d3RIO;\r\nc) CPF (original e uma fotoc\u00f3pia) - OBRIGAT\u00d3RIO; \t\r\nd) certid\u00e3o de casamento, quando ocorrer mudan\u00e7a de nome (original e uma fotoc\u00f3pia);\r\ne) certid\u00e3o de quita\u00e7\u00e3o eleitoral (original), para maiores de 18 anos - OBRIGAT\u00d3RIO;\r\nf) comprovante de quita\u00e7\u00e3o com o servi\u00e7o militar (original e uma fotoc\u00f3pia) - OBRIGAT\u00d3RIO;\r\ng) uma foto recente, no tamanho 3x4 ou 5x7;\r\nh) duas vias do Termo de Ci\u00eancia, disponibilizado no endere\u00e7o eletr\u00f4nico www.sisu.ufg.br - OBRIGAT\u00d3RIO.\r\nII.\tDocumentos Espec\u00edficos de Escolaridade: \r\na)\tcertificado de conclus\u00e3o do Ensino M\u00e9dio ou de curso equivalente, registrado no \u00f3rg\u00e3o competente (original e uma fotoc\u00f3pia), acompanhado do respectivo hist\u00f3rico escolar (original e uma fotoc\u00f3pia) OU, caso n\u00e3o possua o certificado, dever\u00e1 apresentar declara\u00e7\u00e3o de conclus\u00e3o do Ensino M\u00e9dio ou de curso equivalente (original), acompanhado do respectivo hist\u00f3rico escolar (original e uma fotoc\u00f3pia) OU certificado de conclus\u00e3o do Ensino M\u00e9dio por meio da certifica\u00e7\u00e3o do Exame Nacional do Ensino M\u00e9dio (ENEM), do Exame Nacional para Certifica\u00e7\u00e3o de Compet\u00eancias de Jovens e Adultos (ENCCEJA) ou de exames de certifica\u00e7\u00e3o de compet\u00eancia ou de avalia\u00e7\u00e3o de jovens e adultos realizados pelos sistemas estaduais de ensino (original e uma fotoc\u00f3pia). Todos os documentos v\u00e1lidos em territ\u00f3rio nacional e em l\u00edngua portuguesa -OBRIGAT\u00d3RIO. \r\nb)\tO candidato que tenha estudado em escola extinta e n\u00e3o possua Certificado de Conclus\u00e3o do Ensino M\u00e9dio ou de curso equivalente e hist\u00f3rico escolar, devidamente registrado, dever\u00e1 apresentar no ato da Matr\u00edcula presencial documento expedido pelo Acervo de Escolas Extintas que comprove a conclus\u00e3o do Ensino M\u00e9dio ou de curso equivalente (original e fotoc\u00f3pia) - OBRIGAT\u00d3RIO.\r\nIII.\tObserva\u00e7\u00f5es: \r\n1. consulte todas as informa\u00e7\u00f5es sobre a matr\u00edcula na UFG no endere\u00e7o eletr\u00f4nico www.sisu.ufg.br; \r\n2. no Edital de convoca\u00e7\u00e3o para a matr\u00edcula dos candidatos aprovados pelo SiSU\/UFG poder\u00e1 ser solicitada documenta\u00e7\u00e3o complementar ou substitutiva; \r\n3. somente ser\u00e1 matriculado na UFG o candidato aprovado que efetivamente comprovar ter conclu\u00eddo, em conformidade com a legisla\u00e7\u00e3o, o Ensino M\u00e9dio ou curso equivalente que permita a continuidade de estudos em n\u00edvel superior e apresentar a documenta\u00e7\u00e3o exigida, conforme op\u00e7\u00e3o de participa\u00e7\u00e3o\/aprova\u00e7\u00e3o no SiSU;\r\n4. nos casos em que o candidato menor de 18 anos n\u00e3o puder realizar sua Matr\u00edcula presencial, seu representante legal (pai,m\u00e3e ou outro representante), exceto para os candidatos aprovados pela Reserva de Vagas como PPI (Preto, pardo e ind\u00edgena) e cD(com defici\u00eancia), poder\u00e1 realiz\u00e1-la mediante apresenta\u00e7\u00e3o de documento original de identifica\u00e7\u00e3o do representante, neste caso, acompanhado de documento que comprove essa representa\u00e7\u00e3o; \r\n5. ser\u00e1 permitida a Matr\u00edcula presencial por procura\u00e7\u00e3o, exceto para os candidatos aprovados pela Reserva de Vagas como PPI (Preto, pardo e ind\u00edgena) e cD (com defici\u00eancia).\r\n","co_campus":"106560","no_campus":"REGIONAL GOI\u00c2NIA - C\u00c2MPUS SAMAMBAIA","sg_uf_campus":"GO","co_municipio_campus":"5208707","no_municipio_campus":"Goi\u00e2nia","no_ies":"UNIVERSIDADE FEDERAL DE GOI\u00c1S","sg_ies":"UFG","sg_uf_ies":"GO","co_municipio_ies":"5208707","no_municipio_ies":"Goi\u00e2nia","nu_nmin_cn":".01","nu_peso_cn":"1.00","nu_nmin_ch":".01","nu_peso_ch":"2.50","nu_nmin_l":".01","nu_peso_l":"3.00","nu_nmin_m":".01","nu_peso_m":"1.00","nu_nmin_r":".01","nu_peso_r":"2.50","nu_media_minima":".01","ds_complemento":"Eventualmente, poder\u00e3o ser ofertadas disciplinas em turno diferente do especificado no termo de ades\u00e3o. Percentual de vagas para a lei 12.711\/2012 e altera\u00e7\u00f5es utilizados para atender o Artigo 11, par\u00e1grafo \u00fanico da Portaria Normativa n\u00ba 18, de 11\/10\/2012 alterada pelas Portarias MEC n\u00ba 09\/2017 e n\u00ba 1117\/2018.","st_possui_afirmativa":"1","no_sitio_ies":" www.sisu.ufg.br","co_curso_emec":"152","ds_protocolo":"FNEIC2A","ds_autenticidade":"DB3A681FF64C8B4F64F56AA0A0228B12ECDB39C0"},"1":{"co_oferta":"139813","co_termo_adesao":"3242","co_ies":"1036","co_curso":"83998","no_curso":"DESIGN GR\u00c1FICO","qt_vagas_sem1":"29","qt_vagas_sem2":"0","co_grau":"10049","no_grau":"Bacharelado","co_turno":"10070","no_turno":"Noturno","st_turno_m":"0","st_turno_v":"0","st_turno_n":"1","ds_documentacao":"A matr\u00edcula dos candidatos convocados no processo seletivo do SiSU - 1\u00aa edi\u00e7\u00e3o 2020 para ingresso nos cursos de gradua\u00e7\u00e3o presenciais da UEMG por meio da Chamada Regular, ser\u00e1 realizada em duas etapas conforme descri\u00e7\u00e3o: a) PRIMEIRA ETAPA \u00bf PR\u00c9-MATR\u00cdCULA ONLINE: destina-se ao envio da documenta\u00e7\u00e3o m\u00ednima exigida dentro da categoria de vaga em que o candidato est\u00e1 concorrendo, no per\u00edodo e formato indicados no Edital de Convoca\u00e7\u00e3o para a Pr\u00e9-matr\u00edcula. b) SEGUNDA ETAPA \u00bf CONFIRMA\u00c7\u00c3O DE MATR\u00cdCULA: destina-se \u00e0 apresenta\u00e7\u00e3o dos candidatos para efetiva\u00e7\u00e3o da sua matr\u00edcula, nos dias, locais e hor\u00e1rios previstos no Edital de Convoca\u00e7\u00e3o para a Confirma\u00e7\u00e3o da Matr\u00edcula. DOCUMENTA\u00c7\u00c3O PARA CONFIRMA\u00c7\u00c3O DE MATRICULA: a) Requerimento de Matr\u00edcula (modelo fornecido pela Institui\u00e7\u00e3o); b) Declara\u00e7\u00e3o de que n\u00e3o possui v\u00ednculo com outro curso de gradua\u00e7\u00e3o de institui\u00e7\u00e3o de Ensino Superior P\u00fablica (modelo fornecido pela Institui\u00e7\u00e3o); c) Certificado de Conclus\u00e3o do Ensino M\u00e9dio ou curso equivalente (uma c\u00f3pia); d) Hist\u00f3rico Escolar do Ensino M\u00e9dio (uma c\u00f3pia); e) Carteira de Identidade (uma c\u00f3pia); f) CPF ou CIC (uma c\u00f3pia); g) Certid\u00e3o de Nascimento ou Casamento (uma c\u00f3pia); h) Prova de quita\u00e7\u00e3o com o Servi\u00e7o Militar, para os maiores de 18 (dezoito) anos e do sexo masculino (uma c\u00f3pia); i) T\u00edtulo de eleitor e Comprovante de quita\u00e7\u00e3o com as obriga\u00e7\u00f5es eleitorais, para os maiores de 18 (dezoito) anos (uma c\u00f3pia); j) Uma foto 3 x 4 recente. O candidato que n\u00e3o comparecer a qualquer uma das etapas no per\u00edodo, formato, local e hor\u00e1rio, definidos em Edital de Convoca\u00e7\u00e3o, ser\u00e1 considerado desistente para todos os efeitos, sendo convocado o seguinte, em conformidade com o processo classificat\u00f3rio. O candidato dever\u00e1 observar as normas e procedimentos publicados no Edital do Processo Seletivo no Di\u00e1rio Oficial e por meio do endere\u00e7o eletr\u00f4nico www.uemg.br.","co_campus":"3265","no_campus":"ESCOLA DE DESIGN \/ CAMPUS DE BELO HORIZONTE","sg_uf_campus":"MG","co_municipio_campus":"3106200","no_municipio_campus":"Belo Horizonte","no_ies":"UNIVERSIDADE DO ESTADO DE MINAS GERAIS","sg_ies":"UEMG","sg_uf_ies":"MG","co_municipio_ies":"3106200","no_municipio_ies":"Belo Horizonte","nu_nmin_cn":".00","nu_peso_cn":"1.00","nu_nmin_ch":".00","nu_peso_ch":"1.00","nu_nmin_l":".00","nu_peso_l":"1.00","nu_nmin_m":".00","nu_peso_m":"1.00","nu_nmin_r":".01","nu_peso_r":"1.00","nu_media_minima":".01","ds_complemento":"","st_possui_afirmativa":"1","no_sitio_ies":"www.uemg.br","co_curso_emec":"152","ds_protocolo":"Q1TQGVV","ds_autenticidade":"FAFAE82FA0EA65A9BA383CAB8E24121E5965100C"},"2":{"co_oferta":"139812","co_termo_adesao":"3242","co_ies":"1036","co_curso":"83998","no_curso":"DESIGN GR\u00c1FICO","qt_vagas_sem1":"29","qt_vagas_sem2":"0","co_grau":"10049","no_grau":"Bacharelado","co_turno":"10067","no_turno":"Matutino","st_turno_m":"1","st_turno_v":"0","st_turno_n":"0","ds_documentacao":"A matr\u00edcula dos candidatos convocados no processo seletivo do SiSU - 1\u00aa edi\u00e7\u00e3o 2020 para ingresso nos cursos de gradua\u00e7\u00e3o presenciais da UEMG por meio da Chamada Regular, ser\u00e1 realizada em duas etapas conforme descri\u00e7\u00e3o: a) PRIMEIRA ETAPA \u00bf PR\u00c9-MATR\u00cdCULA ONLINE: destina-se ao envio da documenta\u00e7\u00e3o m\u00ednima exigida dentro da categoria de vaga em que o candidato est\u00e1 concorrendo, no per\u00edodo e formato indicados no Edital de Convoca\u00e7\u00e3o para a Pr\u00e9-matr\u00edcula. b) SEGUNDA ETAPA \u00bf CONFIRMA\u00c7\u00c3O DE MATR\u00cdCULA: destina-se \u00e0 apresenta\u00e7\u00e3o dos candidatos para efetiva\u00e7\u00e3o da sua matr\u00edcula, nos dias, locais e hor\u00e1rios previstos no Edital de Convoca\u00e7\u00e3o para a Confirma\u00e7\u00e3o da Matr\u00edcula. DOCUMENTA\u00c7\u00c3O PARA CONFIRMA\u00c7\u00c3O DE MATRICULA: a) Requerimento de Matr\u00edcula (modelo fornecido pela Institui\u00e7\u00e3o); b) Declara\u00e7\u00e3o de que n\u00e3o possui v\u00ednculo com outro curso de gradua\u00e7\u00e3o de institui\u00e7\u00e3o de Ensino Superior P\u00fablica (modelo fornecido pela Institui\u00e7\u00e3o); c) Certificado de Conclus\u00e3o do Ensino M\u00e9dio ou curso equivalente (uma c\u00f3pia); d) Hist\u00f3rico Escolar do Ensino M\u00e9dio (uma c\u00f3pia); e) Carteira de Identidade (uma c\u00f3pia); f) CPF ou CIC (uma c\u00f3pia); g) Certid\u00e3o de Nascimento ou Casamento (uma c\u00f3pia); h) Prova de quita\u00e7\u00e3o com o Servi\u00e7o Militar, para os maiores de 18 (dezoito) anos e do sexo masculino (uma c\u00f3pia); i) T\u00edtulo de eleitor e Comprovante de quita\u00e7\u00e3o com as obriga\u00e7\u00f5es eleitorais, para os maiores de 18 (dezoito) anos (uma c\u00f3pia); j) Uma foto 3 x 4 recente. O candidato que n\u00e3o comparecer a qualquer uma das etapas no per\u00edodo, formato, local e hor\u00e1rio, definidos em Edital de Convoca\u00e7\u00e3o, ser\u00e1 considerado desistente para todos os efeitos, sendo convocado o seguinte, em conformidade com o processo classificat\u00f3rio. O candidato dever\u00e1 observar as normas e procedimentos publicados no Edital do Processo Seletivo no Di\u00e1rio Oficial e por meio do endere\u00e7o eletr\u00f4nico www.uemg.br.","co_campus":"3265","no_campus":"ESCOLA DE DESIGN \/ CAMPUS DE BELO HORIZONTE","sg_uf_campus":"MG","co_municipio_campus":"3106200","no_municipio_campus":"Belo Horizonte","no_ies":"UNIVERSIDADE DO ESTADO DE MINAS GERAIS","sg_ies":"UEMG","sg_uf_ies":"MG","co_municipio_ies":"3106200","no_municipio_ies":"Belo Horizonte","nu_nmin_cn":".00","nu_peso_cn":"1.00","nu_nmin_ch":".00","nu_peso_ch":"1.00","nu_nmin_l":".00","nu_peso_l":"1.00","nu_nmin_m":".00","nu_peso_m":"1.00","nu_nmin_r":".01","nu_peso_r":"1.00","nu_media_minima":".01","ds_complemento":"","st_possui_afirmativa":"1","no_sitio_ies":"www.uemg.br","co_curso_emec":"152","ds_protocolo":"Q1TQGVV","ds_autenticidade":"FAFAE82FA0EA65A9BA383CAB8E24121E5965100C"},"3":{"co_oferta":"134713","co_termo_adesao":"3033","co_ies":"1166","co_curso":"123105","no_curso":"DESIGN GR\u00c1FICO","qt_vagas_sem1":"40","qt_vagas_sem2":"0","co_grau":"10051","no_grau":"Tecnol\u00f3gico","co_turno":"10071","no_turno":"Integral","st_turno_m":"0","st_turno_v":"1","st_turno_n":"1","ds_documentacao":"Para todos os candidatos, independentemente de ser oriundo da ampla concorr\u00eancia ou das a\u00e7\u00f5es afirmativas adotadas pela Institui\u00e7\u00e3o, a matr\u00edcula ser\u00e1 presencial, realizada pelo candidato ou seu procurador legalmente constitu\u00eddo, no Campus em que funciona o curso ofertado para o qual o candidato se inscreveu e foi classificado, devendo este apresentar, no per\u00edodo informado pelo SiSU para a realiza\u00e7\u00e3o de matr\u00edcula, os seguintes documentos: a) 02 (duas) fotos 3x4 (coloridas e recentes); original e c\u00f3pia: b) da certid\u00e3o de nascimento ou casamento; c) da carteira de identidade; d) do CPF; e) do t\u00edtulo de eleitor (para candidatos maiores de 18 (dezoito) anos de idade); f) comprovante de quita\u00e7\u00e3o com o servi\u00e7o militar, ou certificado de reservista, ou de dispensa de incorpora\u00e7\u00e3o (para candidatos do sexo masculino maiores de 18 (dezoito) anos de idade); e g) do certificado de conclus\u00e3o do ensino m\u00e9dio acompanhado do hist\u00f3rico escolar. Caso o candidato concorra \u00e0s vagas destinadas as a\u00e7\u00f5es afirmativas, al\u00e9m dos documentos acima citados, em cada a\u00e7\u00e3o h\u00e1 exig\u00eancia pr\u00f3pria de comprova\u00e7\u00e3o documental sem a qual o candidato perder\u00e1 o direito \u00e0 vaga, mesmo tendo sido classificado dentro das vagas ofertadas na reserva de cotas.","co_campus":"36317","no_campus":"CAMPUS CABEDELO","sg_uf_campus":"PB","co_municipio_campus":"2503209","no_municipio_campus":"Cabedelo","no_ies":"INSTITUTO FEDERAL DE EDUCA\u00c7\u00c3O, CI\u00caNCIA E TECNOLOGIA  DA PARA\u00cdBA","sg_ies":"IFPB","sg_uf_ies":"PB","co_municipio_ies":"2507507","no_municipio_ies":"Jo\u00e3o Pessoa","nu_nmin_cn":".01","nu_peso_cn":"2.00","nu_nmin_ch":".01","nu_peso_ch":"1.00","nu_nmin_l":".01","nu_peso_l":"2.00","nu_nmin_m":".01","nu_peso_m":"2.00","nu_nmin_r":".01","nu_peso_r":"2.00","nu_media_minima":".01","ds_complemento":"https:\/\/estudante.ifpb.edu.br\/cursos\/23","st_possui_afirmativa":"1","no_sitio_ies":"https:\/\/estudante.ifpb.edu.br\/","co_curso_emec":"152","ds_protocolo":"B6UQSRC","ds_autenticidade":"6DF74EFDB5107A3AC5CD885B06AEDD28B445D718"},"4":{"co_oferta":"132485","co_termo_adesao":"2929","co_ies":"1809","co_curso":"71167","no_curso":"DESIGN GR\u00c1FICO","qt_vagas_sem1":"0","qt_vagas_sem2":"40","co_grau":"10051","no_grau":"Tecnol\u00f3gico","co_turno":"10068","no_turno":"Vespertino","st_turno_m":"0","st_turno_v":"1","st_turno_n":"0","ds_documentacao":"1. DOCUMENTA\u00c7\u00c3O B\u00c1SICA DO CANDIDATO \r\na) original para confer\u00eancia e c\u00f3pia simples da Certid\u00e3o de Nascimento ou Casamento Leg\u00edvel, sem emendas ou rasuras; \r\nb) original ou c\u00f3pia autenticada pelo servidor p\u00fablico da institui\u00e7\u00e3o do Certificado de Conclus\u00e3o do Ensino M\u00e9dio (antigo 2\u00ba grau) ou equivalente, e Hist\u00f3rico Escolar ou Declara\u00e7\u00e3o de Conclus\u00e3o com validade para 30 dias (apresentar obrigatoriamente ANEXO do edital do IFPE referente ao TERMO DE CI\u00caNCIA E ACEITA\u00c7\u00c3O DAS REGRAS DE MATR\u00cdCULA CONDICIONAL), leg\u00edvel, sem emendas ou rasuras; (nas p\u00e1ginas autenticadas pelo servidor p\u00fablico da institui\u00e7\u00e3o deve constar obrigatoriamente a identifica\u00e7\u00e3o leg\u00edvel do servidor como nome e SIAPE, carimbo com o dizer \u00bfconfere com original\u00bf e a data);\r\nc) uma foto 3x4 recente; \r\nd) original e c\u00f3pia simples da carteira de identidade (Registro Geral - RG); \r\ne) original e c\u00f3pia simples do CPF; \r\nf) original e c\u00f3pia simples do T\u00edtulo de Eleitor (se maior de 18 anos); \r\ng) original e c\u00f3pia simples do documento comprobat\u00f3rio de regularidade com o Servi\u00e7o Militar (para os maiores de 18 anos do sexo masculino). \r\n1.1 O candidato que realizou seus estudos em institui\u00e7\u00e3o estrangeira, al\u00e9m da documenta\u00e7\u00e3o supracitada dever\u00e1 apresentar original ou c\u00f3pia autenticada pelo servidor p\u00fablico da institui\u00e7\u00e3o do comprovante de conclus\u00e3o de escolaridade do Ensino M\u00e9dio, devidamente revalidado no Brasil na forma da lei (dispensada a revalida\u00e7\u00e3o nos casos de comprovante de conclus\u00e3o de estudos de n\u00edvel m\u00e9dio n\u00e3o t\u00e9cnico, realizado nos pa\u00edses integrantes do Mercosul). \r\n1.2 O candidato que realizou seus estudos em institui\u00e7\u00e3o estrangeira dever\u00e1 apresentar documenta\u00e7\u00e3o devidamente traduzida por tradutor juramentado para o vern\u00e1culo oficial.\r\n","co_campus":"1000181","no_campus":"CAMPUS RECIFE","sg_uf_campus":"PE","co_municipio_campus":"2611606","no_municipio_campus":"Recife","no_ies":"INSTITUTO FEDERAL DE EDUCA\u00c7\u00c3O, CI\u00caNCIA E TECNOLOGIA DE PERNAMBUCO","sg_ies":"IFPE","sg_uf_ies":"PE","co_municipio_ies":"2611606","no_municipio_ies":"Recife","nu_nmin_cn":".00","nu_peso_cn":"1.00","nu_nmin_ch":".00","nu_peso_ch":"1.00","nu_nmin_l":".00","nu_peso_l":"1.00","nu_nmin_m":".00","nu_peso_m":"1.00","nu_nmin_r":".01","nu_peso_r":"1.00","nu_media_minima":".01","ds_complemento":"","st_possui_afirmativa":"1","no_sitio_ies":"ifpe.edu.br","co_curso_emec":"152","ds_protocolo":"N7AI16C","ds_autenticidade":"C021478014A39D0FF88F45B6C6A3C20CE8BA6EB2"},"5":{"co_oferta":"118432","co_termo_adesao":"2390","co_ies":"588","co_curso":"106104","no_curso":"DESIGN GR\u00c1FICO","qt_vagas_sem1":"22","qt_vagas_sem2":"0","co_grau":"10051","no_grau":"Tecnol\u00f3gico","co_turno":"10067","no_turno":"Matutino","st_turno_m":"1","st_turno_v":"0","st_turno_n":"0","ds_documentacao":"a) Fotoc\u00f3pia (acompanhada do original quando n\u00e3o autenticada) do Certificado de Conclus\u00e3o do Ensino M\u00e9dio ou equivalente (T\u00e9cnico de N\u00edvel M\u00e9dio, 2o Grau, Magist\u00e9rio ou Educa\u00e7\u00e3o de Jovens e Adultos), expedidos por Institui\u00e7\u00e3o de Ensino reconhecida por \u00f3rg\u00e3o oficial competente.\r\nb) Fotoc\u00f3pia (acompanhada do original quando n\u00e3o autenticada) do Hist\u00f3rico Escolar completo do Ensino M\u00e9dio, ou equivalente (T\u00e9cnico de N\u00edvel M\u00e9dio, 2o Grau, Magist\u00e9rio ou Educa\u00e7\u00e3o de Jovens e Adultos), com os anexos quando houver, expedidos por Institui\u00e7\u00e3o de Ensino reconhecida por \u00f3rg\u00e3o oficial competente.\r\n      Para candidatos cotistas:\r\nI) O candidato COTISTA selecionado dever\u00e1 comprovar esta condi\u00e7\u00e3o no momento da Entrega de Documenta\u00e7\u00e3o. Esta comprova\u00e7\u00e3o dever\u00e1 ser feita por meio do Hist\u00f3rico Escolar ou da Declara\u00e7\u00e3o de Conclus\u00e3o do Ensino M\u00e9dio ou equivalente, emitida pela Institui\u00e7\u00e3o de Ensino, atestando que o candidato cursou e concluiu com \u00eaxito todas as s\u00e9ries do Ensino M\u00e9dio regular ou equivalente (t\u00e9cnico, magist\u00e9rio ou Educa\u00e7\u00e3o de Jovens e Adultos) em escola(s) p\u00fablica(s) federais, estaduais ou municipais, no Brasil.\r\n \r\nII) O candidato COTISTA selecionado que comprovar a conclus\u00e3o do Ensino M\u00e9dio por meio do certificado de conclus\u00e3o com base no resultado do Exame Nacional do Ensino M\u00e9dio - ENEM, do Exame Nacional para Certifica\u00e7\u00e3o de Compet\u00eancias de Jovens e Adultos - ENCCEJA ou de exames de certifica\u00e7\u00e3o de compet\u00eancia ou de avalia\u00e7\u00e3o de jovens e adultos realizados pelos sistemas estaduais de ensino, dever\u00e3o apresentar tamb\u00e9m, no ato da Entrega de Documenta\u00e7\u00e3o, a declara\u00e7\u00e3o modelo 4 que consta no portal.utfpr.edu.br\/cursos\/estudenautfpr\/sisu.\r\n \r\nc) Fotoc\u00f3pia (acompanhada do original quando n\u00e3o autenticada) da Carteira de Identidade (RG) ou outro documento oficial de identifica\u00e7\u00e3o com foto.\r\nd) Comprova\u00e7\u00e3o da inscri\u00e7\u00e3o no CPF \u00bf O candidato dever\u00e1 apresentar fotoc\u00f3pia do comprovante da inscri\u00e7\u00e3o no CPF impresso a partir do Portal da Secretaria da Receita Federal do Brasil (RFB) na Internet, no endere\u00e7o www.receita.fazenda.gov.br. Esta comprova\u00e7\u00e3o \u00e9 dispens\u00e1vel caso o CPF conste em documento oficial de identifica\u00e7\u00e3o entregue neste ato.\r\ne) Declara\u00e7\u00e3o assinada pelo candidato de que n\u00e3o ocupa vaga em Institui\u00e7\u00e3o P\u00fablica de Ensino (declara\u00e7\u00e3o modelo 1 publicada no portal.utfpr.edu.br\/cursos\/estudenautfpr\/sisu).\r\nf) Fotoc\u00f3pia (acompanhada do original quando n\u00e3o autenticada) de documento que comprove estar em dia com o Servi\u00e7o Militar, para o candidato do sexo masculino maior de 18 anos.\r\ng) Para os candidatos que conclu\u00edram o Ensino M\u00e9dio ou equivalente no exterior, exceto Argentina, Paraguai, Uruguai, Chile e Bol\u00edvia, dever\u00e3o, tamb\u00e9m, apresentar fotoc\u00f3pia do documento de revalida\u00e7\u00e3o e\/ou equival\u00eancia de estudo no Brasil.\r\nh) Para candidatos estrangeiros, apresentar o Registro Nacional Migrat\u00f3rio - RNM (antigo RNE) e o Passaporte com visto de estudante, ou outro documento que, por previs\u00e3o legal, permita que o estrangeiro estude no Brasil.\r\nObserva\u00e7\u00e3o: ver mais informa\u00e7\u00f5es no Edital publicado na p\u00e1gina da UTFPR.","co_campus":"2004801","no_campus":"C\u00c2MPUS CURITIBA - SEDE CENTRO","sg_uf_campus":"PR","co_municipio_campus":"4106902","no_municipio_campus":"Curitiba","no_ies":"UNIVERSIDADE TECNOL\u00d3GICA FEDERAL DO PARAN\u00c1","sg_ies":"UTFPR","sg_uf_ies":"PR","co_municipio_ies":"4106902","no_municipio_ies":"Curitiba","nu_nmin_cn":".01","nu_peso_cn":"1.00","nu_nmin_ch":".01","nu_peso_ch":"1.00","nu_nmin_l":".01","nu_peso_l":"1.00","nu_nmin_m":".01","nu_peso_m":"1.00","nu_nmin_r":".01","nu_peso_r":"1.00","nu_media_minima":".01","ds_complemento":"","st_possui_afirmativa":"1","no_sitio_ies":"http:\/\/portal.utfpr.edu.br\/cursos\/estudenautfpr\/sisu","co_curso_emec":"152","ds_protocolo":"DGPXE3O","ds_autenticidade":"0A19FF8BCA8CC2717990F1B6F5D860D24B20FE8C"},"6":{"co_oferta":"118433","co_termo_adesao":"2390","co_ies":"588","co_curso":"106104","no_curso":"DESIGN GR\u00c1FICO","qt_vagas_sem1":"22","qt_vagas_sem2":"0","co_grau":"10051","no_grau":"Tecnol\u00f3gico","co_turno":"10070","no_turno":"Noturno","st_turno_m":"0","st_turno_v":"0","st_turno_n":"1","ds_documentacao":"a) Fotoc\u00f3pia (acompanhada do original quando n\u00e3o autenticada) do Certificado de Conclus\u00e3o do Ensino M\u00e9dio ou equivalente (T\u00e9cnico de N\u00edvel M\u00e9dio, 2o Grau, Magist\u00e9rio ou Educa\u00e7\u00e3o de Jovens e Adultos), expedidos por Institui\u00e7\u00e3o de Ensino reconhecida por \u00f3rg\u00e3o oficial competente.\r\nb) Fotoc\u00f3pia (acompanhada do original quando n\u00e3o autenticada) do Hist\u00f3rico Escolar completo do Ensino M\u00e9dio, ou equivalente (T\u00e9cnico de N\u00edvel M\u00e9dio, 2o Grau, Magist\u00e9rio ou Educa\u00e7\u00e3o de Jovens e Adultos), com os anexos quando houver, expedidos por Institui\u00e7\u00e3o de Ensino reconhecida por \u00f3rg\u00e3o oficial competente.\r\n      Para candidatos cotistas:\r\nI) O candidato COTISTA selecionado dever\u00e1 comprovar esta condi\u00e7\u00e3o no momento da Entrega de Documenta\u00e7\u00e3o. Esta comprova\u00e7\u00e3o dever\u00e1 ser feita por meio do Hist\u00f3rico Escolar ou da Declara\u00e7\u00e3o de Conclus\u00e3o do Ensino M\u00e9dio ou equivalente, emitida pela Institui\u00e7\u00e3o de Ensino, atestando que o candidato cursou e concluiu com \u00eaxito todas as s\u00e9ries do Ensino M\u00e9dio regular ou equivalente (t\u00e9cnico, magist\u00e9rio ou Educa\u00e7\u00e3o de Jovens e Adultos) em escola(s) p\u00fablica(s) federais, estaduais ou municipais, no Brasil.\r\n \r\nII) O candidato COTISTA selecionado que comprovar a conclus\u00e3o do Ensino M\u00e9dio por meio do certificado de conclus\u00e3o com base no resultado do Exame Nacional do Ensino M\u00e9dio - ENEM, do Exame Nacional para Certifica\u00e7\u00e3o de Compet\u00eancias de Jovens e Adultos - ENCCEJA ou de exames de certifica\u00e7\u00e3o de compet\u00eancia ou de avalia\u00e7\u00e3o de jovens e adultos realizados pelos sistemas estaduais de ensino, dever\u00e3o apresentar tamb\u00e9m, no ato da Entrega de Documenta\u00e7\u00e3o, a declara\u00e7\u00e3o modelo 4 que consta no portal.utfpr.edu.br\/cursos\/estudenautfpr\/sisu.\r\n \r\nc) Fotoc\u00f3pia (acompanhada do original quando n\u00e3o autenticada) da Carteira de Identidade (RG) ou outro documento oficial de identifica\u00e7\u00e3o com foto.\r\nd) Comprova\u00e7\u00e3o da inscri\u00e7\u00e3o no CPF \u00bf O candidato dever\u00e1 apresentar fotoc\u00f3pia do comprovante da inscri\u00e7\u00e3o no CPF impresso a partir do Portal da Secretaria da Receita Federal do Brasil (RFB) na Internet, no endere\u00e7o www.receita.fazenda.gov.br. Esta comprova\u00e7\u00e3o \u00e9 dispens\u00e1vel caso o CPF conste em documento oficial de identifica\u00e7\u00e3o entregue neste ato.\r\ne) Declara\u00e7\u00e3o assinada pelo candidato de que n\u00e3o ocupa vaga em Institui\u00e7\u00e3o P\u00fablica de Ensino (declara\u00e7\u00e3o modelo 1 publicada no portal.utfpr.edu.br\/cursos\/estudenautfpr\/sisu).\r\nf) Fotoc\u00f3pia (acompanhada do original quando n\u00e3o autenticada) de documento que comprove estar em dia com o Servi\u00e7o Militar, para o candidato do sexo masculino maior de 18 anos.\r\ng) Para os candidatos que conclu\u00edram o Ensino M\u00e9dio ou equivalente no exterior, exceto Argentina, Paraguai, Uruguai, Chile e Bol\u00edvia, dever\u00e3o, tamb\u00e9m, apresentar fotoc\u00f3pia do documento de revalida\u00e7\u00e3o e\/ou equival\u00eancia de estudo no Brasil.\r\nh) Para candidatos estrangeiros, apresentar o Registro Nacional Migrat\u00f3rio - RNM (antigo RNE) e o Passaporte com visto de estudante, ou outro documento que, por previs\u00e3o legal, permita que o estrangeiro estude no Brasil.\r\nObserva\u00e7\u00e3o: ver mais informa\u00e7\u00f5es no Edital publicado na p\u00e1gina da UTFPR.","co_campus":"2004801","no_campus":"C\u00c2MPUS CURITIBA - SEDE CENTRO","sg_uf_campus":"PR","co_municipio_campus":"4106902","no_municipio_campus":"Curitiba","no_ies":"UNIVERSIDADE TECNOL\u00d3GICA FEDERAL DO PARAN\u00c1","sg_ies":"UTFPR","sg_uf_ies":"PR","co_municipio_ies":"4106902","no_municipio_ies":"Curitiba","nu_nmin_cn":".01","nu_peso_cn":"1.00","nu_nmin_ch":".01","nu_peso_ch":"1.00","nu_nmin_l":".01","nu_peso_l":"1.00","nu_nmin_m":".01","nu_peso_m":"1.00","nu_nmin_r":".01","nu_peso_r":"1.00","nu_media_minima":".01","ds_complemento":"","st_possui_afirmativa":"1","no_sitio_ies":"http:\/\/portal.utfpr.edu.br\/cursos\/estudenautfpr\/sisu","co_curso_emec":"152","ds_protocolo":"DGPXE3O","ds_autenticidade":"0A19FF8BCA8CC2717990F1B6F5D860D24B20FE8C"},"7":{"co_oferta":"132712","co_termo_adesao":"3011","co_ies":"634","co_curso":"31368","no_curso":"DESIGN GR\u00c1FICO","qt_vagas_sem1":"19","qt_vagas_sem2":"0","co_grau":"10049","no_grau":"Bacharelado","co_turno":"10068","no_turno":"Vespertino","st_turno_m":"0","st_turno_v":"1","st_turno_n":"0","ds_documentacao":"DOCUMENTOS PARA MATR\u00cdCULA (Conforme Edital de Matr\u00edcula a ser publicado pela IES, no seguinte endere\u00e7o: https:\/\/wp.ufpel.edu.br\/sisu\/editais\/):\r\n\r\n-Ficha de cadastro preenchida, impressa e assinada (Disponibilizada em:\r\nhttps:\/\/cobalto.ufpel.edu.br\/academico\/processoSeletivo\/fichaOnline, conforme edital);\r\n-C\u00f3pia simples da certid\u00e3o de nascimento ao casamento;\r\n-Declara\u00e7\u00e3o de ci\u00eancia da confirma\u00e7\u00e3o de matr\u00edcula (Disponibilizada, conforme edital de matr\u00edcula);\r\n\r\n-C\u00f3pia simples da Carteira de Identidade atualizada, de modo que seja poss\u00edvel o reconhecimento por foto e assinatura;\r\n\r\n-C\u00f3pia simples de documento que comprove estar em dia com a justi\u00e7a eleitoral;\r\n\r\n-C\u00f3pia simples do CPF;\r\n\r\n-C\u00f3pia simples de documento que comprove estar em dia com as obriga\u00e7\u00f5es militares;\r\n\r\n-C\u00f3pia simples acompanhada do original** do Hist\u00f3rico Escolar do Ensino M\u00e9dio;\r\n\r\n-C\u00f3pia simples acompanhada do original** do Certificado de Conclus\u00e3o do Ensino M\u00e9dio ou do Diplomado Ensino M\u00e9dio (Este documento pode fazer parte do hist\u00f3rico);\r\n\r\n-Candidatos que tenham realizado estudos equivalentes ao Ensino M\u00e9dio, no todo ou em parte, no exterior, devem apresentar Declara\u00e7\u00e3o de Equival\u00eancia de Estudos, conforme Resolu\u00e7\u00e3o n\u00ba 317\/2011, do Conselho Estadual de Educa\u00e7\u00e3o\/RS;\r\n\r\n- Os documentos estrangeiros dever\u00e3o ser autenticados pela Autoridade Consular Brasileira, no pa\u00eds de origem, e acompanhados da respectiva tradu\u00e7\u00e3o oficial, caso necess\u00e1rio (L\u00edngua diferente do Portugu\u00eas ou Espanhol);\r\n\r\n- C\u00f3pia simples do passaporte e visto de perman\u00eancia no Brasil, ou da carteira nacional de estrangeiro (em se tratando de candidato estrangeiro).\r\n\r\n**Na impossibilidade de apresentar o original, a c\u00f3pia dever\u00e1 ser autenticada em cart\u00f3rio.\r\n\r\nA Lei 12.089, de 11 de novembro de 2009, Pro\u00edbe que uma mesma pessoa ocupe 02 (duas) vagas simultaneamente em institui\u00e7\u00f5es p\u00fablicas de ensino superior.\r\n\r\nCandidatos que j\u00e1 ocupem vaga em algum curso da UFPel, dever\u00e3o cancelar a matr\u00edcula anterior (o que, n\u00e3o ocorrendo, acarretar\u00e1 automaticamente o cancelamento da matr\u00edcula mais recente), valendo como comunica\u00e7\u00e3o prevista no artigo 3\u00ba da Lei 12.089 a assinatura na ficha de inscri\u00e7\u00e3o.\r\n\r\nCandidatos que j\u00e1 ocupem vaga em outra institui\u00e7\u00e3o p\u00fablica de ensino superior ou vaga no PROUNI ter\u00e3o o prazo de 5 (cinco) dias \u00fateis a contar do primeiro dia \u00fatil posterior \u00e0 efetiva\u00e7\u00e3o da matr\u00edcula para cancelar o v\u00ednculo na institui\u00e7\u00e3o de origem.\r\n\r\n* QUEM PODE ENTREGAR A DOCUMENTA\u00c7\u00c3O\r\n\r\nPara candidatos menores de 18 anos:\r\n\r\n- o pr\u00f3prio candidato; - pai, m\u00e3e ou representante legal com comprova\u00e7\u00e3o atrav\u00e9s de documento com foto;\r\n\r\n- terceiros com procura\u00e7\u00e3o assistida com firma reconhecida em cart\u00f3rio.\r\n\r\nPara candidatos maiores de 18 anos:\r\n\r\n- o pr\u00f3prio candidato;\r\n\r\n- pai, m\u00e3e ou terceiros; todos atrav\u00e9s de procura\u00e7\u00e3o com firma reconhecida em cart\u00f3rio.\r\n\r\nVeja modelo de procura\u00e7\u00e3o conforme edital.\r\n\r\nIMPORTANTE: Candidatos ingressantes nas vagas reservadas (Lei N\u00ba 12.711\/2012) dever\u00e3o comprovar a realiza\u00e7\u00e3o integral do ensino m\u00e9dio em escola p\u00fablica e ter\u00e3o a matr\u00edcula condicionada \u00e0 aprova\u00e7\u00e3o de sua situa\u00e7\u00e3o de cotista, conforme op\u00e7\u00e3o de modalidade realizada na inscri\u00e7\u00e3o, a saber : Cotas Sociais - Aprova\u00e7\u00e3o do N\u00facleo de Servi\u00e7o Social da PRAE; Cotas \u00e9tnico-raciais - Aprova\u00e7\u00e3o da CCICE e Cotas para pessoas com defici\u00eancia - Aprova\u00e7\u00e3o do NAI.","co_campus":"1046994","no_campus":"CENTRO DE ARTES","sg_uf_campus":"RS","co_municipio_campus":"4314407","no_municipio_campus":"Pelotas","no_ies":"UNIVERSIDADE FEDERAL DE PELOTAS","sg_ies":"UFPEL","sg_uf_ies":"RS","co_municipio_ies":"4314407","no_municipio_ies":"Pelotas","nu_nmin_cn":".00","nu_peso_cn":"1.00","nu_nmin_ch":".00","nu_peso_ch":"1.00","nu_nmin_l":".00","nu_peso_l":"1.00","nu_nmin_m":".00","nu_peso_m":"1.00","nu_nmin_r":".01","nu_peso_r":"1.00","nu_media_minima":".01","ds_complemento":"","st_possui_afirmativa":"1","no_sitio_ies":"https:\/\/wp.ufpel.edu.br\/sisu\/","co_curso_emec":"152","ds_protocolo":"XXQIUT8","ds_autenticidade":"D863C6EFAD57C45583BC8E652187544942F25690"},"8":{"co_oferta":"119300","co_termo_adesao":"2472","co_ies":"43","co_curso":"54163","no_curso":"DESIGN GR\u00c1FICO","qt_vagas_sem1":"5","qt_vagas_sem2":"0","co_grau":"10049","no_grau":"Bacharelado","co_turno":"10071","no_turno":"Integral","st_turno_m":"1","st_turno_v":"1","st_turno_n":"0","ds_documentacao":"a) \u00bf Diploma ou Certificado de Conclus\u00e3o do Ensino M\u00e9dio e Hist\u00f3rico Escolar ou Certificado de Curso de Educa\u00e7\u00e3o de Jovens e Adultos (EJA) desde que atendam rigorosamente as determina\u00e7\u00f5es da Lei 9.394\/96 ou Certifica\u00e7\u00e3o do Exame Nacional do Ensino M\u00e9dio \u00bf ENEM, desde que atendam as determina\u00e7\u00f5es da Portaria MEC n\u00ba 10, de 23 de maio de 2012 e da Portaria INEP n\u00ba 179, de 28 de abril de 2014 e altera\u00e7\u00f5es ou Certifica\u00e7\u00e3o do Exame Nacional de Jovens e Adultos do Ensino M\u00e9dio \u00bf ENCCEJA ou Diploma ou Certificado de Conclus\u00e3o do Ensino Superior e Hist\u00f3rico Escolar; b) certid\u00e3o de quita\u00e7\u00e3o eleitoral; c) Certid\u00e3o de nascimento;d) Certificado de Alistamento Militar, no caso de alunos do sexo masculino;  \r\ne) Comprova\u00e7\u00e3o da inscri\u00e7\u00e3o no CPF; Carteira de identidade; Comprovante de vacina\u00e7\u00e3o contra rub\u00e9ola, para candidato do sexo feminino;Atestado m\u00e9dico comprobat\u00f3rio de sua condi\u00e7\u00e3o de sa\u00fade, especificando sua aptid\u00e3o \u00e0 pr\u00e1tica de exerc\u00edcios f\u00edsicos para os cursos de Engenharia Mec\u00e2nica; Qu\u00edmica; Engenharia de Produ\u00e7\u00e3o \u00bf Habilita\u00e7\u00e3o:  Mec\u00e2nica, Agronomia e Educa\u00e7\u00e3o F\u00edsica \u00bf Licenciatura\/Bacharelado;O optante pelo Programa de A\u00e7\u00f5es Afirmativas, op\u00e7\u00e3o Escola P\u00fablica dever\u00e1 comprovar no ato da matr\u00edcula, que cursou integralmente o Ensino M\u00e9dio em institui\u00e7\u00f5es p\u00fablicas municipais, estaduais ou federais gratuitas, por meio de Diploma ou Certificado de Conclus\u00e3o e Hist\u00f3rico Escolar do Ensino M\u00e9dio; O optante pelo Programa de A\u00e7\u00f5es Afirmativas op\u00e7\u00e3o Negros, dever\u00e1, no ato da matr\u00edcula, assinar documento de autodeclara\u00e7\u00e3o que possui fen\u00f3tipo que o caracteriza na sociedade como pertencente ao grupo racial negro.   ","co_campus":"657701","no_campus":"CENTRO DE ARTES - CEART CAMPUS I","sg_uf_campus":"SC","co_municipio_campus":"4205407","no_municipio_campus":"Florian\u00f3polis","no_ies":"FUNDA\u00c7\u00c3O UNIVERSIDADE DO ESTADO DE SANTA CATARINA","sg_ies":"UDESC","sg_uf_ies":"SC","co_municipio_ies":"4205407","no_municipio_ies":"Florian\u00f3polis","nu_nmin_cn":".00","nu_peso_cn":"1.00","nu_nmin_ch":".00","nu_peso_ch":"1.00","nu_nmin_l":".00","nu_peso_l":"1.00","nu_nmin_m":".00","nu_peso_m":"1.00","nu_nmin_r":".01","nu_peso_r":"1.00","nu_media_minima":".01","ds_complemento":"","st_possui_afirmativa":"1","no_sitio_ies":"www.udesc.br","co_curso_emec":"152","ds_protocolo":"XUHRJL3","ds_autenticidade":"CD522AA930486742B68E048EF8065142F7D4EB27"}}